universal_sdk/__init__.py
universal_sdk/cli.py
universal_sdk/client.py
universal_sdk/exceptions.py
universal_sdk/utils.py
universal_sdk-0.1.0.dist-info/METADATA
universal_sdk-0.1.0.dist-info/WHEEL
universal_sdk-0.1.0.dist-info/entry_points.txt
universal_sdk-0.1.0.dist-info/top_level.txt
universal_sdk-0.1.0.dist-info/RECORD
