Metadata-Version: 2.4
Name: universal-sdk
Version: 0.1.0
Summary: Universal SDK for File Text Extractor API
Home-page: https://github.com/yourusername/universal_sdk
Author: Your Name
Author-email: Your Name <youremail@example.com>
License: MIT
Requires-Python: >=3.8
Requires-Dist: requests
Requires-Dist: python-dotenv
Requires-Dist: fastapi
Requires-Dist: uvicorn
